lodestarmcp/__init__.py
lodestarmcp/_base_client.py
lodestarmcp/_client.py
lodestarmcp/_compat.py
lodestarmcp/_constants.py
lodestarmcp/_exceptions.py
lodestarmcp/_files.py
lodestarmcp/_models.py
lodestarmcp/_qs.py
lodestarmcp/_resource.py
lodestarmcp/_response.py
lodestarmcp/_streaming.py
lodestarmcp/_types.py
lodestarmcp/_version.py
lodestarmcp/py.typed
lodestarmcp/_utils/__init__.py
lodestarmcp/_utils/_logs.py
lodestarmcp/_utils/_proxy.py
lodestarmcp/_utils/_reflection.py
lodestarmcp/_utils/_resources_proxy.py
lodestarmcp/_utils/_streams.py
lodestarmcp/_utils/_sync.py
lodestarmcp/_utils/_transform.py
lodestarmcp/_utils/_typing.py
lodestarmcp/_utils/_utils.py
lodestarmcp/lib/.keep
lodestarmcp/resources/__init__.py
lodestarmcp/resources/appraisal_modifiers_php.py
lodestarmcp/resources/closing_cost_calculations_php.py
lodestarmcp/resources/counties_php.py
lodestarmcp/resources/endorsements_php.py
lodestarmcp/resources/geocode_check_php.py
lodestarmcp/resources/login.py
lodestarmcp/resources/property_tax_php.py
lodestarmcp/resources/questions_php.py
lodestarmcp/resources/sub_agents_php.py
lodestarmcp/resources/townships_php.py
lodestarmcp/types/__init__.py
lodestarmcp/types/appraisal_modifiers_php_get_available_params.py
lodestarmcp/types/appraisal_modifiers_php_get_available_response.py
lodestarmcp/types/closing_cost_calculations_php_calculate_params.py
lodestarmcp/types/closing_cost_calculations_php_calculate_response.py
lodestarmcp/types/counties_php_get_available_counties_params.py
lodestarmcp/types/counties_php_get_available_counties_response.py
lodestarmcp/types/document_param.py
lodestarmcp/types/endorsements_php_list_params.py
lodestarmcp/types/endorsements_php_list_response.py
lodestarmcp/types/geocode_check_php_check_params.py
lodestarmcp/types/geocode_check_php_check_response.py
lodestarmcp/types/line1101item.py
lodestarmcp/types/line1201item.py
lodestarmcp/types/line1203item.py
lodestarmcp/types/loan_info_param.py
lodestarmcp-2.0.0.dist-info/METADATA
lodestarmcp-2.0.0.dist-info/WHEEL
lodestarmcp-2.0.0.dist-info/licenses/LICENSE
lodestarmcp-2.0.0.dist-info/RECORD
